Metadata-Version: 2.1
Name: shdlc-sps30
Version: 0.1
Summary: SHDLC Driver for Sensirion SPS30
Home-page: https://github.com/metebalci/sensirion-shdlc-sps30
Author: Mete Balci
Author-email: metebalci@gmail.com
License: GPLv3
Keywords: sensirion shdlc driver sps30
Platform: UNKNOWN
Classifier: Intended Audience :: Developers
Classifier: License :: OSI Approved :: GNU General Public License v3 (GPLv3)
Classifier: Programming Language :: Python :: 3 :: Only
Classifier: Topic :: System :: Hardware :: Hardware Drivers
